PyAissistant/__init__.py
PyAissistant/DeepSeek/__init__.py
PyAissistant/DeepSeek/chat_completion.py
PyAissistant/DeepSeek/deepseek.py
PyAissistant/DeepSeek/deepseek_demo.py
PyAissistant/DeepSeek/fim_completion.py
PyAissistant/Extension/__init__.py
PyAissistant/Extension/ai_code_tool.py
PyAissistant/Extension/ai_coder.py
PyAissistant/Extension/ai_extension.py
PyAissistant/Extension/ai_tool_pack.py
PyAissistant/PyChatBot/Chat.py
PyAissistant/PyChatBot/__console_extend.py
PyAissistant/PyChatBot/__init__.py
PyAissistant/PyChatBot/ai_executor.py
PyAissistant/PyChatBot/chat_api.py
PyAissistant/PyChatBot/chat_bot_util.py
PyAissistant/PyChatBot/chat_on_consle.py
PyAissistant/PyChatBot/deek_seek_openai.py
PyAissistant/PyChatBot/deep_seek_bot.py
PyAissistant/PyChatBot/deep_seek_message_process.py
PyAissistant/PyChatBot/ollama_bot.py
PyAissistant/ai_assist/__init__.py
PyAissistant/ai_assist/ai_tools.py
PyAissistant-0.1.20.dist-info/LICENSE.md
PyAissistant-0.1.20.dist-info/METADATA
PyAissistant-0.1.20.dist-info/WHEEL
PyAissistant-0.1.20.dist-info/top_level.txt
PyAissistant-0.1.20.dist-info/RECORD
