Metadata-Version: 2.1
Name: PyAissistant
Version: 0.1.20
Summary: A Python package designed to provide a user-friendly interface for AI developers working with Python. This package aims to streamline the integration of AI functionalities into your projects, making it easier to leverage advanced AI capabilities
Home-page: https://github.com/HinxCorporation/PyAissistant
Author: Hinx Vietti(Lai)
Author-email: Hinxvietti@gmail.com
Classifier: Programming Language :: Python :: 3
Classifier: License :: OSI Approved :: MIT License
Classifier: Operating System :: OS Independent
Requires-Python: >=3.9
License-File: LICENSE.md
Requires-Dist: ollama-api ~=0.1.1
Requires-Dist: psutil ~=6.0.0
Requires-Dist: tabulate ~=0.9.0
Requires-Dist: colorama ~=0.4.6
Requires-Dist: requests ~=2.32.3
Requires-Dist: openai ~=1.40.0
